alphaessaio/__init__.py
alphaessaio/client.py
alphaessaio/response.py
alphaess_aio-0.2.0.dist-info/LICENSE
alphaess_aio-0.2.0.dist-info/METADATA
alphaess_aio-0.2.0.dist-info/WHEEL
alphaess_aio-0.2.0.dist-info/top_level.txt
alphaess_aio-0.2.0.dist-info/RECORD
