Metadata-Version: 2.1
Name: alphaess-aio
Version: 0.2.0
Summary: Sends get and post requests to available AlphaCloud API endpoints.
Author-email: Markus Ziegler <frage_n@web.de>
Maintainer-email: Markus Ziegler <frage_n@web.de>
License: MIT License
Project-URL: Repository, https://github.com/zeguramente/alphaess-aio
Keywords: alphaess,api
Classifier: Development Status :: 4 - Beta
Classifier: Programming Language :: Python
Requires-Python: >=3.10
License-File: LICENSE
Requires-Dist: aiohttp>=3.9.3
Requires-Dist: pydantic>=2.10.3
Provides-Extra: test
Requires-Dist: pytest; extra == "test"
Requires-Dist: pytest-mock; extra == "test"
Requires-Dist: pytest-asyncio; extra == "test"
Requires-Dist: pytest-aiohttp; extra == "test"
Provides-Extra: lint
Requires-Dist: ruff>=0.4.2; extra == "lint"
